{"id":37,"key":"bs5\/qanda","name":"translate:bs5_module_qanda","output":"","input":"<?php\r\n\r\n$mform = MForm::factory();\r\n\r\n$qanda_categories = qanda_company::query()->find();\r\n$options = [];\r\nforeach ($qanda_categories as $qanda_company) {\r\n    $options[$qanda_company->getId()] = $qanda_company->getName();\r\n}\r\n\r\n$field = $mform->addMultiSelectField(1, $options);\r\n$field->setLabel('translate:test');\r\n\r\n$qandas = qanda::query()->find();\r\n$options = [];\r\nforeach ($qandas as $qanda) {\r\n    $options[$qanda->getId()] = $qanda->getQuestion();\r\n}\r\n\r\n$field = $mform->addMultiSelectField(2, $options);\r\n$field->setLabel('translate:test');\r\n\/\/ parse form\r\necho $mform->show();\r\n","createdate":"2022-04-19 14:56:01","createuser":"console","updatedate":"2023-04-25 14:50:41","updateuser":"mail@alexplus.de","attributes":null,"revision":0}