{"id":36,"key":"bs5_global_settings","name":"Inhalt | Globale Einstellung","output":"<section class=\"modul modul-bs-global-settings py-5\">\r\n    <div class=\"container bg-white p-3 bs5-text shadow\">\r\n    <?php\r\n    \r\n$field = rex_sql::factory()->getArray(\"SELECT F.title as title, F.name as name, T.label as type FROM rex_global_settings_field F LEFT JOIN rex_global_settings_type T on F.type_id = T.id WHERE name = :name ORDER BY title\", [\"name\" => \"REX_VALUE[1]\"]);\r\n            \r\nswitch ($field[0][\"type\"]) {\r\n    case \"textarea\":\r\n        echo rex_global_settings::getValue($field[0]['name']);\r\n        break;\r\n    case \"text\":\r\n        break;\r\n    case \"REX_MEDIA_WIDGET\":\r\n        break;\r\n    case \"REX_MEDIALIST_WIDGET\":\r\n        break;\r\n    case \"REX_LINK_WIDGET\":\r\n        break;\r\n    case \"REX_LINKLIST_WIDGET\":\r\n        break;\r\n    default:\r\n        break;\r\n}\r\n    ?>\r\n    <\/div>\r\n<\/section>\r\n","input":"<?php\r\n\r\n$mform = MForm::factory();\r\n\r\n$sql_options = rex_sql::factory()->getArray(\"SELECT title, CONCAT(name) as value FROM rex_global_settings_field ORDER BY title\");\r\n$options = [];\r\nforeach($sql_options as $sql_option) {\r\n    $options[$sql_option['value']] = $sql_option['title'];\r\n}\r\n\r\n\r\n$field = $mform->addSelectField(1, $options);\r\n$field->setLabel('translate:test');\r\n\r\n\r\n\/\/ parse form\r\necho $mform->show();\r\n","createdate":"2022-04-20 13:20:46","createuser":"plus_bs5","updatedate":"2022-04-20 13:20:46","updateuser":"plus_bs5","attributes":null,"revision":0}